gerbolyze/__init__.py
gerbolyze/__main__.py
gerbolyze/protoboard.py
gerbolyze-3.1.9.data/scripts/gerbolyze
gerbolyze-3.1.9.dist-info/LICENSE
gerbolyze-3.1.9.dist-info/METADATA
gerbolyze-3.1.9.dist-info/WHEEL
gerbolyze-3.1.9.dist-info/top_level.txt
gerbolyze-3.1.9.dist-info/RECORD
