Metadata-Version: 2.1
Name: gerbolyze
Version: 3.1.9
Summary: A high-resolution image-to-PCB converter. Gerbolyze plots SVG, PNG and JPG onto existing gerber files. It handles almost the full SVG spec and deals with text, path outlines, patterns, arbitrary paths with self-intersections and holes, etc. fully automatically. It can vectorize raster images both by contour tracing and by grayscale dithering. All processing is done at the vector level without intermediate conversions to raster images accurately preserving the input.
Home-page: https://github.com/jaseg/gerbolyze
Author: jaseg
Author-email: gerbonara@jaseg.de
License: AGPLv3
Project-URL: Source Code, https://git.jaseg.de/gerbolyze
Project-URL: Bug Tracker, https://github.com/jaseg/gerbolyze/issues
Classifier: Development Status :: 5 - Production/Stable
Classifier: Environment :: Console
Classifier: Intended Audience :: Manufacturing
Classifier: Intended Audience :: Science/Research
Classifier: Intended Audience :: Religion
Classifier: Intended Audience :: Developers
Classifier: License :: OSI Approved :: GNU Affero General Public License v3 or later (AGPLv3+)
Classifier: Natural Language :: English
Classifier: Topic :: Scientific/Engineering :: Electronic Design Automation (EDA)
Classifier: Topic :: Utilities
License-File: LICENSE
Requires-Dist: gerbonara (>=1.2.0)
Requires-Dist: beautifulsoup4
Requires-Dist: numpy
Requires-Dist: python-slugify
Requires-Dist: lxml
Requires-Dist: click
Requires-Dist: svg-flatten-wasi
